pyextmath/__init__.py
pyextmath/pyextmath.py
pyextmath_selcukwashere-0.0.1.dist-info/LICENSE
pyextmath_selcukwashere-0.0.1.dist-info/METADATA
pyextmath_selcukwashere-0.0.1.dist-info/WHEEL
pyextmath_selcukwashere-0.0.1.dist-info/top_level.txt
pyextmath_selcukwashere-0.0.1.dist-info/RECORD
